modules/__init__.py
modules/genome_quality_filter.py
modules/genome_simulator.py
modules/msa.py
modules/parameter_checks.py
modules/primer_generation.py
modules/probe_generation.py
modules/sensitivity_check.py
modules/utils.py
modules/validator.py
modules/visualizer.py
olivar-0.0.1.data/scripts/olivar
olivar-0.0.1.dist-info/LICENSE
olivar-0.0.1.dist-info/METADATA
olivar-0.0.1.dist-info/WHEEL
olivar-0.0.1.dist-info/top_level.txt
olivar-0.0.1.dist-info/RECORD
