Metadata-Version: 2.1
Name: olivar
Version: 0.0.1
Summary: Olivar pipeline
Home-page: https://gitlab.com/treangen.lab/olivar
Author: Treangen Lab
Author-email: acd7+olivar@rice.edu
License: UNKNOWN
Platform: UNKNOWN
Classifier: Programming Language :: Python :: 3
Classifier: License :: OSI Approved :: MIT License
Classifier: Operating System :: OS Independent
Requires-Python: >=3.7
Requires-Dist: pip
Requires-Dist: pipdeptree
Requires-Dist: pandas
Requires-Dist: certifi
Requires-Dist: chardet
Requires-Dist: docopt
Requires-Dist: idna
Requires-Dist: pipreqs
Requires-Dist: requests
Requires-Dist: urllib3
Requires-Dist: yarg
Requires-Dist: biopython
Requires-Dist: jinja2
Requires-Dist: pysam
Requires-Dist: pyvcf
Requires-Dist: tqdm
